shellgenius/__init__.py
shellgenius/cli.py
shellgenius/gpt_integration.py
ShellGenius-0.1.16.dist-info/LICENSE
ShellGenius-0.1.16.dist-info/METADATA
ShellGenius-0.1.16.dist-info/WHEEL
ShellGenius-0.1.16.dist-info/entry_points.txt
ShellGenius-0.1.16.dist-info/top_level.txt
ShellGenius-0.1.16.dist-info/RECORD
