Metadata-Version: 2.1
Name: ShellGenius
Version: 0.1.16
Summary: ShellGenius is a tool to generate shell commands from description in natural language.
Author: Sébastien De Revière
License: Apache License 2.0
License-File: LICENSE
Requires-Dist: click
Requires-Dist: openai <1.0
Requires-Dist: rich
Requires-Dist: tiktoken
